<?xml version="1.0"?>
<!DOCTYPE render SYSTEM "render.dtd">
<render>
<!--
	<attachment_descriptions>

		<attachment name="test">
			<format value="RG16F" />
			<samples value="1" />
			<loadOp value="VK_ATTACHMENT_LOAD_OP_CLEAR" />
			<storeOp value="VK_ATTACHMENT_STORE_OP_STORE" />
			<stencilLoadOp value="VK_ATTACHMENT_LOAD_OP_DONT_CARE" />
			<stencilStoreOp value="VK_ATTACHMENT_STORE_OP_DONT_CARE" />
			<initialLayout value="VK_IMAGE_LAYOUT_COLOR_ATTACHMENT_OPTIMAL" />
			<initialLayout value="VK_IMAGE_LAYOUT_COLOR_ATTACHMENT_OPTIMAL" />
		</attachment>

		<attachment name="depth">
			<format value="RG16F" />
			<samples value="1" />
			<loadOp value="VK_ATTACHMENT_LOAD_OP_CLEAR" />
			<storeOp value="VK_ATTACHMENT_STORE_OP_STORE" />
			<stencilLoadOp value="VK_ATTACHMENT_LOAD_OP_DONT_CARE" />
			<stencilStoreOp value="VK_ATTACHMENT_STORE_OP_DONT_CARE" />
			<initialLayout value="VK_IMAGE_LAYOUT_COLOR_ATTACHMENT_OPTIMAL" />
			<initialLayout value="VK_IMAGE_LAYOUT_COLOR_ATTACHMENT_OPTIMAL" />
		</attachment>

	</attachment_descriptions>
-->
	<targets>
		<texture name="depth" format="GL_DEPTH_COMPONENT32F" />
		<texture name="shadow_map" format="GL_DEPTH_COMPONENT32F" />
		<texture name="normals" format="GL_RGBA16F" />
		<texture name="lights_diffuse" format="GL_R11F_G11F_B10F" />
		<texture name="lights_specular" format="GL_R11F_G11F_B10F" />
		<texture name="HDR" format="GL_R11F_G11F_B10F" />
		<texture name="LDR" format="GL_RGBA8" />
		<texture name="bloom1" format="GL_R11F_G11F_B10F" size_divisor="4" />
		<texture name="bloom2" format="GL_R11F_G11F_B10F" size_divisor="4" />
		<texture name="luminance1" format="GL_RG16F" />
		<texture name="luminance2" format="GL_RG16F" />
	</targets>

	<framebuffers>
		<framebuffer name="shadow-map">
			<output texture="shadow_map" />
		</framebuffer>
		<framebuffer name="normals-earlyZ">
			<output texture="depth" /> <!-- early z-cull -->
			<output texture="normals" />
		</framebuffer>
		<framebuffer name="lights">
			<output texture="lights_diffuse" />
			<output texture="lights_specular" />
		</framebuffer>
		<framebuffer name="bloom_br">
			<output texture="bloom1" />
		</framebuffer>
		<framebuffer name="bloom_bh">
			<output texture="bloom2" />
		</framebuffer>
		<framebuffer name="bloom_bv">
			<output texture="bloom1" />
		</framebuffer>
		<framebuffer name="HDR-earlyZ">
			<output texture="depth" /> <!-- early z-cull -->
			<output texture="HDR" />
		</framebuffer>
		<framebuffer name="HDR">
			<output texture="HDR" />
		</framebuffer>
		<framebuffer name="LDR">
			<output texture="LDR" />
		</framebuffer>
		<framebuffer name="luminance">
			<output texture="luminance1" />
		</framebuffer>
	</framebuffers>

</render>
